orderly/__init__.py
orderly/clean/__init__.py
orderly/clean/__main__.py
orderly/clean/cleaner.py
orderly/data/__init__.py
orderly/data/solvents.csv
orderly/data/solvents.py
orderly/data/test_data/extracted_ord_test_data_dont_trust_labelling/all_molecule_names.csv
orderly/data/test_data/extracted_ord_test_data_dont_trust_labelling/extract_config.json
orderly/data/test_data/extracted_ord_test_data_dont_trust_labelling/extracted_ords/750_astrazeneca_eln_dataset.parquet
orderly/data/test_data/extracted_ord_test_data_dont_trust_labelling/extracted_ords/ord_dataset-0c75d67751634f0594b24b9f498b77c2.parquet
orderly/data/test_data/extracted_ord_test_data_dont_trust_labelling/extracted_ords/ord_dataset-cbcc4048add7468e850b6ec42549c70d.parquet
orderly/data/test_data/extracted_ord_test_data_dont_trust_labelling/extracted_ords/synthesis_of_islatravir_by_biocatalytic_cascade.parquet
orderly/data/test_data/extracted_ord_test_data_dont_trust_labelling/extracted_ords/uspto-grants-1976_01.parquet
orderly/data/test_data/extracted_ord_test_data_dont_trust_labelling/extracted_ords/uspto-grants-1978_12.parquet
orderly/data/test_data/extracted_ord_test_data_dont_trust_labelling/extracted_ords/uspto-grants-1979_09.parquet
orderly/data/test_data/extracted_ord_test_data_dont_trust_labelling/extracted_ords/uspto-grants-1980_08.parquet
orderly/data/test_data/extracted_ord_test_data_dont_trust_labelling/extracted_ords/uspto-grants-1982_08.parquet
orderly/data/test_data/extracted_ord_test_data_dont_trust_labelling/extracted_ords/uspto-grants-1986_09.parquet
orderly/data/test_data/extracted_ord_test_data_dont_trust_labelling/extracted_ords/uspto-grants-1995_11.parquet
orderly/data/test_data/extracted_ord_test_data_dont_trust_labelling/extracted_ords/uspto-grants-2001_07.parquet
orderly/data/test_data/extracted_ord_test_data_dont_trust_labelling/molecule_names/molecules_750_astrazeneca_eln_dataset.csv
orderly-1.0.0.dist-info/LICENSE
orderly-1.0.0.dist-info/METADATA
orderly-1.0.0.dist-info/WHEEL
orderly-1.0.0.dist-info/RECORD
