Metadata-Version: 2.1
Name: orderly
Version: 1.0.0
Summary: Extraction and cleaning of chemical reactions data from ORD
Home-page: https://github.com/sustainable-processes/ORDerly
License: MIT
Keywords: ord-schema,RDKit,ord-data,chemical-reactions
Author: Daniel S. Wigh
Author-email: dsw46@cam.ac.uk
Maintainer: Daniel S. Wigh
Maintainer-email: dsw46@cam.ac.uk
Requires-Python: >=3.10,<4.0
Classifier: License :: OSI Approved :: MIT License
Classifier: Programming Language :: Python :: 3
Classifier: Programming Language :: Python :: 3.10
Classifier: Programming Language :: Python :: 3.11
Requires-Dist: click (>=8.1.3,<9.0.0)
Requires-Dist: fastparquet (>=2023.2.0,<2024.0.0)
Requires-Dist: joblib (>=1.2.0,<2.0.0)
Requires-Dist: ord-schema (>=0.3.44,<0.4.0)
Requires-Dist: psutil (>=5.9.4,<6.0.0)
Requires-Dist: rdkit (>=2022.9.5,<2023.0.0)
Requires-Dist: tqdm (>=4.65.0,<5.0.0)
Requires-Dist: types-requests (>=2.31.0.1,<3.0.0.0)
Project-URL: Repository, https://github.com/sustainable-processes/ORDerly
